<?xml version="1.0" encoding="UTF-8"?>
<con:soapui-project id="cee2a670-c058-4357-8093-9ac5f985e039" activeEnvironment="Default" name="Client" resourceRoot="" soapui-version="5.3.0" abortOnError="false" runType="SEQUENTIAL" xmlns:con="http://eviware.com/soapui/config"><con:settings/><con:interface xsi:type="con:WsdlInterface" id="37f2d007-2656-4233-8436-64b2c1e0aa57" wsaVersion="NONE" name="ConversionPortBinding" type="wsdl" bindingName="{http://www.fst.univ-lorraine.fr}ConversionPortBinding" soapVersion="1_1" anonymous="optional" definition="http://localhost:8080/?wsdl" xmlns:xsi="http://www.w3.org/2001/XMLSchema-instance"><con:settings/><con:definitionCache type="TEXT" rootPart="http://localhost:8080/?wsdl"><con:part><con:url>http://localhost:8080/?wsdl</con:url><con:content><![CDATA[<!--Published by JAX-WS RI (http://jax-ws.java.net). RI's version is JAX-WS RI 2.2.9-b130926.1035 svn-revision#5f6196f2b90e9460065a4c2f4e30e065b245e51e.-->
<!--Generated by JAX-WS RI (http://jax-ws.java.net). RI's version is JAX-WS RI 2.2.9-b130926.1035 svn-revision#5f6196f2b90e9460065a4c2f4e30e065b245e51e.-->
<definitions targetNamespace="http://www.fst.univ-lorraine.fr" name="ConversionService" xmlns:wsu="http://docs.oasis-open.org/wss/2004/01/oasis-200401-wss-wssecurity-utility-1.0.xsd" xmlns:wsp="http://www.w3.org/ns/ws-policy" xmlns:wsp1_2="http://schemas.xmlsoap.org/ws/2004/09/policy" xmlns:wsam="http://www.w3.org/2007/05/addressing/metadata" xmlns:soap="http://schemas.xmlsoap.org/wsdl/soap/" xmlns:tns="http://www.fst.univ-lorraine.fr" xmlns:xsd="http://www.w3.org/2001/XMLSchema" xmlns="http://schemas.xmlsoap.org/wsdl/">
  <types>
    <xsd:schema>
      <xsd:import namespace="http://www.fst.univ-lorraine.fr" schemaLocation="http://localhost:8080/?xsd=1"/>
    </xsd:schema>
  </types>
  <message name="conversion">
    <part name="parameters" element="tns:conversion"/>
  </message>
  <message name="conversionResponse">
    <part name="parameters" element="tns:conversionResponse"/>
  </message>
  <portType name="Conversion">
    <operation name="conversion">
      <input wsam:Action="convert" message="tns:conversion"/>
      <output wsam:Action="http://www.fst.univ-lorraine.fr/Conversion/conversionResponse" message="tns:conversionResponse"/>
    </operation>
  </portType>
  <binding name="ConversionPortBinding" type="tns:Conversion">
    <soap:binding transport="http://schemas.xmlsoap.org/soap/http" style="document"/>
    <operation name="conversion">
      <soap:operation soapAction="convert"/>
      <input>
        <soap:body use="literal"/>
      </input>
      <output>
        <soap:body use="literal"/>
      </output>
    </operation>
  </binding>
  <service name="ConversionService">
    <port name="ConversionPort" binding="tns:ConversionPortBinding">
      <soap:address location="http://localhost:8080/"/>
    </port>
  </service>
</definitions>]]></con:content><con:type>http://schemas.xmlsoap.org/wsdl/</con:type></con:part><con:part><con:url>http://localhost:8080/?xsd=1</con:url><con:content><![CDATA[<!--Published by JAX-WS RI (http://jax-ws.java.net). RI's version is JAX-WS RI 2.2.9-b130926.1035 svn-revision#5f6196f2b90e9460065a4c2f4e30e065b245e51e.-->
<xs:schema version="1.0" targetNamespace="http://www.fst.univ-lorraine.fr" xmlns:tns="http://www.fst.univ-lorraine.fr" xmlns:xs="http://www.w3.org/2001/XMLSchema">
  <xs:element name="conversion" type="tns:conversion"/>
  <xs:element name="conversionResponse" type="tns:conversionResponse"/>
  <xs:complexType name="conversion">
    <xs:sequence>
      <xs:element name="amount" type="xs:double"/>
    </xs:sequence>
  </xs:complexType>
  <xs:complexType name="conversionResponse">
    <xs:sequence>
      <xs:element name="return" type="xs:double"/>
    </xs:sequence>
  </xs:complexType>
</xs:schema>]]></con:content><con:type>http://www.w3.org/2001/XMLSchema</con:type></con:part></con:definitionCache><con:endpoints><con:endpoint>http://localhost:8080/</con:endpoint></con:endpoints><con:operation id="311c9505-3441-4755-ac8e-aca4cc58afe4" isOneWay="false" action="convert" name="conversion" bindingOperationName="conversion" type="Request-Response" inputName="" receivesAttachments="false" sendsAttachments="false" anonymous="optional"><con:settings/><con:call id="05d8c0dc-c487-4baf-91d8-61cf69970e0f" name="Request 1"><con:settings><con:setting id="com.eviware.soapui.impl.wsdl.WsdlRequest@request-headers">&lt;xml-fragment/></con:setting></con:settings><con:encoding>UTF-8</con:encoding><con:endpoint>http://localhost:8080/</con:endpoint><con:request><![CDATA[<soapenv:Envelope xmlns:soapenv="http://schemas.xmlsoap.org/soap/envelope/" xmlns:fst="http://www.fst.univ-lorraine.fr">
   <soapenv:Header/>
   <soapenv:Body>
      <fst:conversion>
         <amount>500</amount>
      </fst:conversion>
   </soapenv:Body>
</soapenv:Envelope>]]></con:request><con:credentials><con:authType>No Authorization</con:authType></con:credentials><con:jmsConfig JMSDeliveryMode="PERSISTENT"/><con:jmsPropertyConfig/><con:wsaConfig mustUnderstand="NONE" version="200508" action="convert"/><con:wsrmConfig version="1.2"/></con:call></con:operation></con:interface><con:properties/><con:wssContainer/><con:oAuth2ProfileContainer/><con:oAuth1ProfileContainer/></con:soapui-project>